changelogbuilder/__init__.py
changelogbuilder/changelogbuilder.py
changelogbuilder-1.0.0.dist-info/DESCRIPTION.rst
changelogbuilder-1.0.0.dist-info/METADATA
changelogbuilder-1.0.0.dist-info/RECORD
changelogbuilder-1.0.0.dist-info/WHEEL
changelogbuilder-1.0.0.dist-info/entry_points.txt
changelogbuilder-1.0.0.dist-info/metadata.json
changelogbuilder-1.0.0.dist-info/top_level.txt
