Metadata-Version: 2.0
Name: changelogbuilder
Version: 1.0.0
Summary: ChangeLog Builder application
Home-page: http://gitlab.org/secstate/changelogbuilder
Author: Colin Powell
Author-email: colin.powell@fiveq.com
License: BSD
Platform: OS Independent
Classifier: Development Status :: 4 - Beta
Classifier: Framework :: Django
Classifier: Intended Audience :: Developers
Classifier: License :: OSI Approved :: BSD License
Classifier: Operating System :: OS Independent
Classifier: Programming Language :: Python
Classifier: Topic :: Internet :: WWW/HTTP
Classifier: Topic :: Internet :: WWW/HTTP :: Dynamic Content
Requires-Dist: gitpython (>=2)
